clikraken/__about__.py
clikraken/__init__.py
clikraken/__main__.py
clikraken/clikraken.py
clikraken/clikraken_cmd.py
clikraken/clikraken_utils.py
clikraken/global_vars.py
clikraken/log_utils.py
clikraken/api/__init__.py
clikraken/api/api_utils.py
clikraken/api/private/__init__.py
clikraken/api/private/cancel_order.py
clikraken/api/private/get_balance.py
clikraken/api/private/get_deposit_addresses.py
clikraken/api/private/get_deposit_methods.py
clikraken/api/private/get_ledgers.py
clikraken/api/private/get_trade_balance.py
clikraken/api/private/list_closed_orders.py
clikraken/api/private/list_open_orders.py
clikraken/api/private/list_open_positions.py
clikraken/api/private/place_order.py
clikraken/api/private/trades.py
clikraken/api/public/__init__.py
clikraken/api/public/asset_pairs.py
clikraken/api/public/depth.py
clikraken/api/public/last_trades.py
clikraken/api/public/ohlc.py
clikraken/api/public/ticker.py
clikraken-0.8.5.dist-info/LICENSE
clikraken-0.8.5.dist-info/METADATA
clikraken-0.8.5.dist-info/WHEEL
clikraken-0.8.5.dist-info/entry_points.txt
clikraken-0.8.5.dist-info/top_level.txt
clikraken-0.8.5.dist-info/RECORD
