Metadata-Version: 2.1
Name: clikraken
Version: 0.8.5
Summary: Command-line client for the Kraken exchange
Home-page: https://github.com/zertrin/clikraken
Author: Marc Gallet
Author-email: zertrin@gmail.com
License: Apache License, Version 2.0
Platform: UNKNOWN
Classifier: Programming Language :: Python
Classifier: Development Status :: 4 - Beta
Classifier: License :: OSI Approved :: Apache Software License
Classifier: Operating System :: OS Independent
Classifier: Programming Language :: Python :: 3
Classifier: Programming Language :: Python :: 3.5
Classifier: Programming Language :: Python :: 3.6
Classifier: Programming Language :: Python :: 3.7
Classifier: Programming Language :: Python :: 3.8
Classifier: Programming Language :: Python :: 3.9
Classifier: Programming Language :: Python :: 3.10
Classifier: Programming Language :: Python :: 3.11
Classifier: Topic :: Office/Business :: Financial
Classifier: Topic :: Office/Business :: Financial :: Investment
Requires-Dist: arrow <0.14
Requires-Dist: colorlog
Requires-Dist: krakenex <3.0,>=2.2.1
Requires-Dist: tabulate
